{"site":"joomla.org","outcomes":{"aoomla.org":false,"boomla.org":true,"doomla.org":false,"eoomla.org":false,"foomla.org":true,"goomla.org":true,"hoomla.org":true,"ioomla.org":true,"koomla.org":true,"loomla.org":true,"moomla.org":false,"noomla.org":false,"ooomla.org":false,"poomla.org":true,"qoomla.org":false,"roomla.org":false,"soomla.org":false,"toomla.org":false,"uoomla.org":false,"voomla.org":true,"woomla.org":false,"xoomla.org":false,"yoomla.org":true,"zoomla.org":true,"1oomla.org":false,"2oomla.org":false,"3oomla.org":false,"4oomla.org":false,"5oomla.org":false,"6oomla.org":false,"7oomla.org":false,"8oomla.org":false,"9oomla.org":false,"0oomla.org":false,"jaomla.org":true,"jbomla.org":false,"jcomla.org":false,"jdomla.org":false,"jfomla.org":false,"jgomla.org":false,"jhomla.org":false,"jiomla.org":true,"jjomla.org":false,"jkomla.org":true,"jlomla.org":false,"jmomla.org":false,"jnomla.org":false,"jpomla.org":false,"jqomla.org":false,"jromla.org":false,"jsomla.org":false,"jtomla.org":false,"juomla.org":false,"jvomla.org":false,"jwomla.org":false,"jxomla.org":false,"jyomla.org":false,"jzomla.org":false,"j1omla.org":false,"j2omla.org":false,"j3omla.org":false,"j5omla.org":false,"j6omla.org":false,"j7omla.org":false,"j8omla.org":false,"j9omla.org":false,"j0omla.org":true,"joamla.org":false,"jobmla.org":false,"jocmla.org":false,"joemla.org":false,"jofmla.org":false,"jogmla.org":false,"johmla.org":false,"joimla.org":false,"jojmla.org":false,"jokmla.org":false,"jolmla.org":false,"jommla.org":true,"jonmla.org":false,"jopmla.org":false,"joqmla.org":false,"jormla.org":false,"josmla.org":false,"jotmla.org":false,"joumla.org":false,"jovmla.org":false,"jowmla.org":false,"joxmla.org":false,"joymla.org":false,"jozmla.org":false,"jo1mla.org":false,"jo2mla.org":false,"jo3mla.org":false,"jo4mla.org":false,"jo5mla.org":false,"jo6mla.org":false,"jo7mla.org":false,"jo8mla.org":false,"jo9mla.org":false,"jo0mla.org":false,"jooala.org":false,"joobla.org":false,"joocla.org":false,"joodla.org":false,"jooela.org":false,"joofla.org":false,"joogla.org":false,"joohla.org":false,"jooila.org":false,"joojla.org":false,"jookla.org":false,"joonla.org":true,"jooola.org":false,"joopla.org":true,"jooqla.org":false,"joorla.org":false,"joosla.org":false,"jootla.org":false,"jooula.org":false,"joovla.org":false,"joowla.org":false,"jooxla.org":false,"jooyla.org":false,"joozla.org":false,"joo1la.org":false,"joo2la.org":false,"joo3la.org":false,"joo4la.org":false,"joo5la.org":false,"joo6la.org":false,"joo7la.org":false,"joo8la.org":false,"joo9la.org":false,"joo0la.org":false,"joomaa.org":false,"joomba.org":false,"joomca.org":false,"joomda.org":false,"joomea.org":false,"joomfa.org":true,"joomga.org":false,"joomha.org":false,"joomia.org":true,"joomja.org":false,"joomma.org":false,"joomna.org":false,"joomoa.org":false,"joompa.org":false,"joomqa.org":false,"joomra.org":false,"joomsa.org":false,"joomta.org":false,"joomua.org":false,"joomva.org":false,"joomwa.org":false,"joomxa.org":false,"joomya.org":false,"joomza.org":false,"joom1a.org":false,"joom3a.org":false,"joom4a.org":false,"joom5a.org":false,"joom6a.org":false,"joom7a.org":false,"joom8a.org":false,"joom9a.org":false,"joom0a.org":false,"joomlb.org":false,"joomlc.org":false,"joomld.org":false,"joomle.org":false,"joomlf.org":false,"joomlg.org":false,"joomlh.org":false,"joomli.org":false,"joomlj.org":false,"joomlk.org":false,"joomlm.org":false,"joomln.org":false,"joomlo.org":true,"joomlp.org":false,"joomlq.org":false,"joomlr.org":false,"joomls.org":false,"joomlt.org":false,"joomlu.org":false,"joomlv.org":false,"joomlw.org":false,"joomlx.org":false,"joomly.org":false,"joomlz.org":false,"jooml1.org":false,"jooml2.org":false,"jooml3.org":false,"jooml4.org":false,"jooml5.org":false,"jooml6.org":false,"jooml7.org":false,"jooml8.org":false,"jooml9.org":false,"jooml0.org":false}}