{"site":"redtube.com","outcomes":{"bedtube.com":true,"cedtube.com":true,"dedtube.com":true,"eedtube.com":true,"fedtube.com":true,"gedtube.com":true,"hedtube.com":true,"iedtube.com":false,"jedtube.com":true,"kedtube.com":true,"ledtube.com":true,"medtube.com":true,"nedtube.com":true,"oedtube.com":false,"pedtube.com":true,"qedtube.com":false,"sedtube.com":true,"tedtube.com":true,"uedtube.com":true,"vedtube.com":true,"wedtube.com":true,"xedtube.com":true,"yedtube.com":true,"zedtube.com":true,"1edtube.com":false,"2edtube.com":true,"3edtube.com":false,"4edtube.com":true,"5edtube.com":true,"6edtube.com":false,"7edtube.com":false,"8edtube.com":false,"9edtube.com":false,"0edtube.com":false,"radtube.com":true,"rbdtube.com":true,"rcdtube.com":true,"rddtube.com":true,"rfdtube.com":true,"rgdtube.com":true,"rhdtube.com":false,"ridtube.com":true,"rjdtube.com":false,"rkdtube.com":false,"rldtube.com":true,"rmdtube.com":false,"rndtube.com":true,"rodtube.com":true,"rpdtube.com":false,"rqdtube.com":false,"rrdtube.com":true,"rsdtube.com":true,"rudtube.com":true,"rvdtube.com":false,"rwdtube.com":true,"rxdtube.com":true,"rydtube.com":false,"rzdtube.com":false,"r1dtube.com":false,"r2dtube.com":false,"r3dtube.com":true,"r4dtube.com":true,"r5dtube.com":false,"r6dtube.com":false,"r7dtube.com":false,"r8dtube.com":false,"r9dtube.com":false,"r0dtube.com":false,"reatube.com":true,"rebtube.com":true,"rectube.com":true,"reetube.com":true,"reftube.com":true,"regtube.com":true,"rehtube.com":true,"reitube.com":true,"rejtube.com":false,"rektube.com":true,"reltube.com":true,"remtube.com":true,"rentube.com":true,"reotube.com":true,"reptube.com":true,"reqtube.com":true,"rertube.com":true,"restube.com":true,"rettube.com":true,"reutube.com":true,"revtube.com":true,"rewtube.com":true,"rextube.com":true,"reytube.com":true,"reztube.com":true,"re1tube.com":false,"re2tube.com":false,"re3tube.com":false,"re4tube.com":false,"re5tube.com":false,"re6tube.com":false,"re7tube.com":false,"re8tube.com":false,"re9tube.com":false,"re0tube.com":false,"redaube.com":false,"redbube.com":true,"redcube.com":true,"reddube.com":true,"redeube.com":true,"redfube.com":true,"redgube.com":true,"redhube.com":true,"rediube.com":true,"redjube.com":true,"redkube.com":true,"redlube.com":true,"redmube.com":false,"rednube.com":true,"redoube.com":true,"redpube.com":true,"redqube.com":true,"redrube.com":true,"redsube.com":true,"reduube.com":true,"redvube.com":false,"redwube.com":false,"redxube.com":false,"redyube.com":true,"redzube.com":true,"red1ube.com":false,"red2ube.com":false,"red3ube.com":false,"red4ube.com":false,"red5ube.com":true,"red6ube.com":true,"red7ube.com":false,"red8ube.com":false,"red9ube.com":false,"red0ube.com":false,"redtabe.com":true,"redtbbe.com":true,"redtcbe.com":false,"redtdbe.com":true,"redtebe.com":true,"redtfbe.com":false,"redtgbe.com":false,"redthbe.com":true,"redtibe.com":true,"redtjbe.com":false,"redtkbe.com":true,"redtlbe.com":true,"redtmbe.com":false,"redtnbe.com":true,"redtobe.com":true,"redtpbe.com":false,"redtqbe.com":false,"redtrbe.com":true,"redtsbe.com":false,"redttbe.com":true,"redtvbe.com":true,"redtwbe.com":true,"redtxbe.com":true,"redtybe.com":true,"redtzbe.com":true,"redt1be.com":false,"redt2be.com":false,"redt3be.com":false,"redt4be.com":true,"redt5be.com":false,"redt6be.com":false,"redt7be.com":true,"redt8be.com":true,"redt9be.com":false,"redt0be.com":false,"redtuae.com":true,"redtuce.com":true,"redtude.com":true,"redtuee.com":true,"redtufe.com":false,"redtuge.com":true,"redtuhe.com":true,"redtuie.com":true,"redtuje.com":false,"redtuke.com":true,"redtule.com":true,"redtume.com":true,"redtune.com":true,"redtuoe.com":false,"redtupe.com":true,"redtuqe.com":true,"redture.com":true,"redtuse.com":true,"redtute.com":true,"redtuue.com":true,"redtuve.com":true,"redtuwe.com":true,"redtuxe.com":false,"redtuye.com":true,"redtuze.com":false,"redtu1e.com":false,"redtu2e.com":false,"redtu3e.com":false,"redtu4e.com":false,"redtu5e.com":false,"redtu6e.com":false,"redtu7e.com":false,"redtu8e.com":false,"redtu0e.com":false,"redtuba.com":true,"redtubb.com":true,"redtubc.com":true,"redtubd.com":true,"redtubf.com":true,"redtubg.com":false,"redtubh.com":false,"redtubi.com":true,"redtubj.com":false,"redtubk.com":false,"redtubl.com":true,"redtubm.com":true,"redtubn.com":true,"redtubo.com":true,"redtubp.com":true,"redtubq.com":true,"redtubr.com":true,"redtubs.com":true,"redtubt.com":true,"redtubu.com":true,"redtubv.com":true,"redtubw.com":true,"redtubx.com":true,"redtuby.com":true,"redtubz.com":true,"redtub1.com":false,"redtub2.com":false,"redtub3.com":true,"redtub4.com":true,"redtub5.com":false,"redtub6.com":false,"redtub7.com":false,"redtub8.com":true,"redtub9.com":false,"redtub0.com":false}}