{"site":"xcar.com.cn","outcomes":{"acar.com.cn":true,"bcar.com.cn":true,"ccar.com.cn":true,"dcar.com.cn":true,"ecar.com.cn":false,"fcar.com.cn":true,"gcar.com.cn":false,"hcar.com.cn":true,"icar.com.cn":true,"jcar.com.cn":false,"kcar.com.cn":false,"lcar.com.cn":true,"mcar.com.cn":true,"ncar.com.cn":false,"ocar.com.cn":true,"pcar.com.cn":true,"qcar.com.cn":true,"rcar.com.cn":true,"scar.com.cn":true,"tcar.com.cn":false,"ucar.com.cn":true,"vcar.com.cn":true,"wcar.com.cn":true,"ycar.com.cn":true,"zcar.com.cn":true,"1car.com.cn":true,"2car.com.cn":true,"3car.com.cn":false,"4car.com.cn":true,"5car.com.cn":false,"6car.com.cn":false,"7car.com.cn":false,"8car.com.cn":true,"9car.com.cn":false,"0car.com.cn":false,"xaar.com.cn":true,"xbar.com.cn":true,"xdar.com.cn":false,"xear.com.cn":true,"xfar.com.cn":true,"xgar.com.cn":false,"xhar.com.cn":false,"xiar.com.cn":false,"xjar.com.cn":false,"xkar.com.cn":false,"xlar.com.cn":false,"xmar.com.cn":false,"xnar.com.cn":false,"xoar.com.cn":false,"xpar.com.cn":false,"xqar.com.cn":false,"xrar.com.cn":false,"xsar.com.cn":false,"xtar.com.cn":false,"xuar.com.cn":false,"xvar.com.cn":true,"xwar.com.cn":false,"xxar.com.cn":false,"xyar.com.cn":false,"xzar.com.cn":false,"x2ar.com.cn":false,"x3ar.com.cn":false,"x4ar.com.cn":false,"x5ar.com.cn":false,"x6ar.com.cn":false,"x7ar.com.cn":false,"x8ar.com.cn":false,"x9ar.com.cn":false,"x0ar.com.cn":false,"xccr.com.cn":false,"xcdr.com.cn":false,"xcer.com.cn":false,"xcfr.com.cn":false,"xcgr.com.cn":true,"xchr.com.cn":true,"xcir.com.cn":false,"xcjr.com.cn":true,"xckr.com.cn":false,"xclr.com.cn":false,"xcmr.com.cn":false,"xcnr.com.cn":false,"xcor.com.cn":false,"xcpr.com.cn":true,"xcqr.com.cn":false,"xcrr.com.cn":true,"xcsr.com.cn":true,"xctr.com.cn":false,"xcur.com.cn":false,"xcvr.com.cn":false,"xcwr.com.cn":false,"xcxr.com.cn":false,"xcyr.com.cn":false,"xczr.com.cn":true,"xc1r.com.cn":false,"xc2r.com.cn":false,"xc3r.com.cn":false,"xc4r.com.cn":false,"xc5r.com.cn":false,"xc6r.com.cn":false,"xc7r.com.cn":false,"xc8r.com.cn":false,"xc9r.com.cn":false,"xc0r.com.cn":false,"xcaa.com.cn":true,"xcab.com.cn":false,"xcac.com.cn":false,"xcad.com.cn":true,"xcae.com.cn":true,"xcaf.com.cn":true,"xcag.com.cn":true,"xcah.com.cn":false,"xcai.com.cn":false,"xcaj.com.cn":false,"xcak.com.cn":false,"xcal.com.cn":false,"xcam.com.cn":true,"xcan.com.cn":true,"xcao.com.cn":false,"xcaq.com.cn":false,"xcas.com.cn":false,"xcat.com.cn":true,"xcau.com.cn":false,"xcav.com.cn":true,"xcaw.com.cn":false,"xcax.com.cn":false,"xcay.com.cn":false,"xcaz.com.cn":false,"xca2.com.cn":false,"xca3.com.cn":false,"xca4.com.cn":false,"xca5.com.cn":false,"xca6.com.cn":false,"xca7.com.cn":false,"xca8.com.cn":false,"xca9.com.cn":false,"xca0.com.cn":false}}